autoflow/__init__.py
autoflow/autoflowconfig.py
autoflow/config_converter.py
autoflow/datasets.py
autoflow/evaluate.py
autoflow/fit-produce.py
autoflow/fit-score.py
autoflow/fit_produce.py
autoflow/fit_score.py
autoflow/fittodrop.py
autoflow/gama_classifier_config.py
autoflow/gama_regressor_config.py
autoflow/gama_tsf_config.py
autoflow/gama_tsf_reduced_config.py
autoflow/generate-pipeline-yaml.py
autoflow/healthcheck.py
autoflow/inspect-dataset.py
autoflow/main.py
autoflow/nbest.py
autoflow/optimizer.py
autoflow/pipeline.py
autoflow/pipeline_optimizer.py
autoflow/tpot-classifier-config.py
autoflow/tpot-regressor-config.py
autoflow/validate-pipeline.py
autoflow/whitelist_classification.json
autoflow/whitelist_regression.json
autoflow/common/__init__.py
autoflow/common/config.py
autoflow/config/__init__.py
autoflow/config/d3m_grid.py
autoflow/config/generate_config.py
autoflow/config/load_config.py
autoflow/pipelines/__init__.py
autoflow/pipelines/base.py
autoflow/pipelines/community_detection_jhu.py
autoflow/pipelines/graph_matching_jhu.py
autoflow/pipelines/image_recognition.py
autoflow/pipelines/library.py
autoflow/pipelines/link_prediction_jhu.py
autoflow/pipelines/multi_table_sri.py
autoflow/pipelines/semi_supervised.py
autoflow/pipelines/single_table.py
autoflow/pipelines/single_table_cmu.py
autoflow/pipelines/single_table_lupi.py
autoflow/pipelines/single_table_semi.py
autoflow/pipelines/single_table_sri.py
autoflow/pipelines/time_series_class.py
autoflow/pipelines/time_series_forecast.py
autoflow/pipelines/vertex_classification.py
autoflow/pipelines/vertex_classification_jhu.py
autoflow/pipelines/video_classification.py
autoflow/ta2-ta3/__init__.py
autoflow/ta2-ta3/client.py
autoflow/ta2-ta3/client2.py
autoflow/ta2-ta3/core_pb2.py
autoflow/ta2-ta3/core_pb2_grpc.py
autoflow/ta2-ta3/id_tracker.py
autoflow/ta2-ta3/message_converter.py
autoflow/ta2-ta3/message_to_pipeline.py
autoflow/ta2-ta3/pipeline_pb2.py
autoflow/ta2-ta3/pipeline_pb2_grpc.py
sri_autoflow-1.0.3.dist-info/METADATA
sri_autoflow-1.0.3.dist-info/WHEEL
sri_autoflow-1.0.3.dist-info/entry_points.txt
sri_autoflow-1.0.3.dist-info/top_level.txt
sri_autoflow-1.0.3.dist-info/RECORD
